{"config":{"output_file":null,"full_docs":false,"pub_only":true,"reachable_only":true,"distro_crate":false,"signatures":false,"borrow_data":false},"version":"0.19.1","compilation":{"directory":"/home/santiago/.cargo/registry/src/github.com-1ecc6299db9ec823/sha2-0.5.3","program":"/home/santiago/.rustup/toolchains/stable-x86_64-unknown-linux-gnu/bin/rls","arguments":["--crate-name","sha2","/home/santiago/.cargo/registry/src/github.com-1ecc6299db9ec823/sha2-0.5.3/src/lib.rs","--json=diagnostic-rendered-ansi","--crate-type","lib","--emit=dep-info,metadata","-C","embed-bitcode=no","-C","debuginfo=2","-C","metadata=edc16b41bafe8b76","-C","extra-filename=-edc16b41bafe8b76","--out-dir","/home/santiago/Repositories/rust-projects/sha_256/target/rls/debug/deps","-L","dependency=/home/santiago/Repositories/rust-projects/sha_256/target/rls/debug/deps","--extern","byte_tools=/home/santiago/Repositories/rust-projects/sha_256/target/rls/debug/deps/libbyte_tools-d8d6dfd8101bc1db.rmeta","--extern","digest=/home/santiago/Repositories/rust-projects/sha_256/target/rls/debug/deps/libdigest-77f0ff81388517c7.rmeta","--extern","digest_buffer=/home/santiago/Repositories/rust-projects/sha_256/target/rls/debug/deps/libdigest_buffer-33d17322587c85fd.rmeta","--extern","fake_simd=/home/santiago/Repositories/rust-projects/sha_256/target/rls/debug/deps/libfake_simd-c5c41fc1692f5d67.rmeta","--extern","generic_array=/home/santiago/Repositories/rust-projects/sha_256/target/rls/debug/deps/libgeneric_array-afc041b4020ec1c3.rmeta","--cap-lints","allow","--error-format=json","--sysroot","/home/santiago/.rustup/toolchains/stable-x86_64-unknown-linux-gnu"],"output":"/home/santiago/Repositories/rust-projects/sha_256/target/rls/debug/deps/libsha2-edc16b41bafe8b76.rmeta"},"prelude":{"crate_id":{"name":"sha2","disambiguator":[5963501382300838260,10203731207098308497]},"crate_root":"/home/santiago/.cargo/registry/src/github.com-1ecc6299db9ec823/sha2-0.5.3/src","external_crates":[{"file_name":"/home/santiago/.cargo/registry/src/github.com-1ecc6299db9ec823/sha2-0.5.3/src/lib.rs","num":1,"id":{"name":"core","disambiguator":[9461532395471723626,17649752992216879242]}},{"file_name":"/home/santiago/.cargo/registry/src/github.com-1ecc6299db9ec823/sha2-0.5.3/src/lib.rs","num":2,"id":{"name":"compiler_builtins","disambiguator":[13102141027849022754,10844956084955862736]}},{"file_name":"/home/santiago/.cargo/registry/src/github.com-1ecc6299db9ec823/sha2-0.5.3/src/lib.rs","num":3,"id":{"name":"rustc_std_workspace_core","disambiguator":[10802439125609973726,12056872925128751599]}},{"file_name":"/home/santiago/.cargo/registry/src/github.com-1ecc6299db9ec823/sha2-0.5.3/src/lib.rs","num":4,"id":{"name":"generic_array","disambiguator":[15317744616056217855,854500386998894239]}},{"file_name":"/home/santiago/.cargo/registry/src/github.com-1ecc6299db9ec823/sha2-0.5.3/src/lib.rs","num":5,"id":{"name":"typenum","disambiguator":[15996057349867460478,6617918932531464244]}},{"file_name":"/home/santiago/.cargo/registry/src/github.com-1ecc6299db9ec823/sha2-0.5.3/src/lib.rs","num":6,"id":{"name":"nodrop","disambiguator":[9909790383095245371,8633419827284263714]}},{"file_name":"/home/santiago/.cargo/registry/src/github.com-1ecc6299db9ec823/sha2-0.5.3/src/lib.rs","num":7,"id":{"name":"byte_tools","disambiguator":[16329623374278786819,3960530299174311381]}},{"file_name":"/home/santiago/.cargo/registry/src/github.com-1ecc6299db9ec823/sha2-0.5.3/src/lib.rs","num":8,"id":{"name":"digest","disambiguator":[5788160885054127530,7981793968796277868]}},{"file_name":"/home/santiago/.cargo/registry/src/github.com-1ecc6299db9ec823/sha2-0.5.3/src/lib.rs","num":9,"id":{"name":"digest_buffer","disambiguator":[15049180563130766026,13499863690663578312]}},{"file_name":"/home/santiago/.cargo/registry/src/github.com-1ecc6299db9ec823/sha2-0.5.3/src/lib.rs","num":10,"id":{"name":"fake_simd","disambiguator":[13382927722981383999,15261376607160642010]}}],"span":{"file_name":"/home/santiago/.cargo/registry/src/github.com-1ecc6299db9ec823/sha2-0.5.3/src/lib.rs","byte_start":0,"byte_end":2914,"line_start":1,"line_end":85,"column_start":1,"column_end":66}},"imports":[{"kind":"Use","ref_id":{"krate":8,"index":22},"span":{"file_name":"/home/santiago/.cargo/registry/src/github.com-1ecc6299db9ec823/sha2-0.5.3/src/lib.rs","byte_start":2807,"byte_end":2813,"line_start":83,"line_end":83,"column_start":17,"column_end":23},"alias_span":null,"name":"Digest","value":"","parent":{"krate":0,"index":0}},{"kind":"Use","ref_id":{"krate":0,"index":322},"span":{"file_name":"/home/santiago/.cargo/registry/src/github.com-1ecc6299db9ec823/sha2-0.5.3/src/lib.rs","byte_start":2832,"byte_end":2838,"line_start":84,"line_end":84,"column_start":18,"column_end":24},"alias_span":null,"name":"Sha256","value":"","parent":{"krate":0,"index":0}},{"kind":"Use","ref_id":{"krate":0,"index":327},"span":{"file_name":"/home/santiago/.cargo/registry/src/github.com-1ecc6299db9ec823/sha2-0.5.3/src/lib.rs","byte_start":2840,"byte_end":2846,"line_start":84,"line_end":84,"column_start":26,"column_end":32},"alias_span":null,"name":"Sha224","value":"","parent":{"krate":0,"index":0}},{"kind":"Use","ref_id":{"krate":0,"index":346},"span":{"file_name":"/home/santiago/.cargo/registry/src/github.com-1ecc6299db9ec823/sha2-0.5.3/src/lib.rs","byte_start":2866,"byte_end":2872,"line_start":85,"line_end":85,"column_start":18,"column_end":24},"alias_span":null,"name":"Sha512","value":"","parent":{"krate":0,"index":0}},{"kind":"Use","ref_id":{"krate":0,"index":351},"span":{"file_name":"/home/santiago/.cargo/registry/src/github.com-1ecc6299db9ec823/sha2-0.5.3/src/lib.rs","byte_start":2874,"byte_end":2880,"line_start":85,"line_end":85,"column_start":26,"column_end":32},"alias_span":null,"name":"Sha384","value":"","parent":{"krate":0,"index":0}},{"kind":"Use","ref_id":{"krate":0,"index":361},"span":{"file_name":"/home/santiago/.cargo/registry/src/github.com-1ecc6299db9ec823/sha2-0.5.3/src/lib.rs","byte_start":2882,"byte_end":2896,"line_start":85,"line_end":85,"column_start":34,"column_end":48},"alias_span":null,"name":"Sha512Trunc224","value":"","parent":{"krate":0,"index":0}},{"kind":"Use","ref_id":{"krate":0,"index":356},"span":{"file_name":"/home/santiago/.cargo/registry/src/github.com-1ecc6299db9ec823/sha2-0.5.3/src/lib.rs","byte_start":2898,"byte_end":2912,"line_start":85,"line_end":85,"column_start":50,"column_end":64},"alias_span":null,"name":"Sha512Trunc256","value":"","parent":{"krate":0,"index":0}}],"defs":[{"kind":"Mod","id":{"krate":0,"index":0},"span":{"file_name":"/home/santiago/.cargo/registry/src/github.com-1ecc6299db9ec823/sha2-0.5.3/src/lib.rs","byte_start":0,"byte_end":2914,"line_start":1,"line_end":85,"column_start":1,"column_end":66},"name":"","qualname":"::","value":"/home/santiago/.cargo/registry/src/github.com-1ecc6299db9ec823/sha2-0.5.3/src/lib.rs","parent":null,"children":[{"krate":0,"index":1},{"krate":0,"index":2},{"krate":0,"index":3},{"krate":0,"index":4},{"krate":0,"index":5},{"krate":0,"index":6},{"krate":0,"index":7},{"krate":0,"index":8},{"krate":0,"index":9},{"krate":0,"index":38},{"krate":0,"index":75},{"krate":0,"index":110},{"krate":0,"index":182},{"krate":0,"index":285},{"krate":0,"index":288},{"krate":0,"index":289},{"krate":0,"index":292},{"krate":0,"index":295},{"krate":0,"index":296},{"krate":0,"index":299},{"krate":0,"index":302},{"krate":0,"index":305}],"decl_id":null,"docs":" An implementation of the SHA-2 cryptographic hash algorithms.","sig":null,"attributes":[{"value":"/ An implementation of the SHA-2 cryptographic hash algorithms.","span":{"file_name":"/home/santiago/.cargo/registry/src/github.com-1ecc6299db9ec823/sha2-0.5.3/src/lib.rs","byte_start":0,"byte_end":65,"line_start":1,"line_end":1,"column_start":1,"column_end":66}},{"value":"/","span":{"file_name":"/home/santiago/.cargo/registry/src/github.com-1ecc6299db9ec823/sha2-0.5.3/src/lib.rs","byte_start":66,"byte_end":69,"line_start":2,"line_end":2,"column_start":1,"column_end":4}},{"value":"/ There are 6 standard algorithms specified in the SHA-2 standard:","span":{"file_name":"/home/santiago/.cargo/registry/src/github.com-1ecc6299db9ec823/sha2-0.5.3/src/lib.rs","byte_start":70,"byte_end":138,"line_start":3,"line_end":3,"column_start":1,"column_end":69}},{"value":"/","span":{"file_name":"/home/santiago/.cargo/registry/src/github.com-1ecc6299db9ec823/sha2-0.5.3/src/lib.rs","byte_start":139,"byte_end":142,"line_start":4,"line_end":4,"column_start":1,"column_end":4}},{"value":"/ * `Sha224`, which is the 32-bit `Sha256` algorithm with the result truncated","span":{"file_name":"/home/santiago/.cargo/registry/src/github.com-1ecc6299db9ec823/sha2-0.5.3/src/lib.rs","byte_start":143,"byte_end":223,"line_start":5,"line_end":5,"column_start":1,"column_end":81}},{"value":"/ to 224 bits.","span":{"file_name":"/home/santiago/.cargo/registry/src/github.com-1ecc6299db9ec823/sha2-0.5.3/src/lib.rs","byte_start":224,"byte_end":240,"line_start":6,"line_end":6,"column_start":1,"column_end":17}},{"value":"/ * `Sha256`, which is the 32-bit `Sha256` algorithm.","span":{"file_name":"/home/santiago/.cargo/registry/src/github.com-1ecc6299db9ec823/sha2-0.5.3/src/lib.rs","byte_start":241,"byte_end":296,"line_start":7,"line_end":7,"column_start":1,"column_end":56}},{"value":"/ * `Sha384`, which is the 64-bit `Sha512` algorithm with the result truncated","span":{"file_name":"/home/santiago/.cargo/registry/src/github.com-1ecc6299db9ec823/sha2-0.5.3/src/lib.rs","byte_start":297,"byte_end":377,"line_start":8,"line_end":8,"column_start":1,"column_end":81}},{"value":"/ to 384 bits.","span":{"file_name":"/home/santiago/.cargo/registry/src/github.com-1ecc6299db9ec823/sha2-0.5.3/src/lib.rs","byte_start":378,"byte_end":394,"line_start":9,"line_end":9,"column_start":1,"column_end":17}},{"value":"/ * `Sha512`, which is the 64-bit `Sha512` algorithm.","span":{"file_name":"/home/santiago/.cargo/registry/src/github.com-1ecc6299db9ec823/sha2-0.5.3/src/lib.rs","byte_start":395,"byte_end":450,"line_start":10,"line_end":10,"column_start":1,"column_end":56}},{"value":"/ * `Sha512Trunc224`, which is the 64-bit `Sha512` algorithm with the result","span":{"file_name":"/home/santiago/.cargo/registry/src/github.com-1ecc6299db9ec823/sha2-0.5.3/src/lib.rs","byte_start":451,"byte_end":529,"line_start":11,"line_end":11,"column_start":1,"column_end":79}},{"value":"/ truncated to 224 bits.","span":{"file_name":"/home/santiago/.cargo/registry/src/github.com-1ecc6299db9ec823/sha2-0.5.3/src/lib.rs","byte_start":530,"byte_end":556,"line_start":12,"line_end":12,"column_start":1,"column_end":27}},{"value":"/ * `Sha512Trunc256`, which is the 64-bit `Sha512` algorithm with the result","span":{"file_name":"/home/santiago/.cargo/registry/src/github.com-1ecc6299db9ec823/sha2-0.5.3/src/lib.rs","byte_start":557,"byte_end":635,"line_start":13,"line_end":13,"column_start":1,"column_end":79}},{"value":"/ truncated to 256 bits.","span":{"file_name":"/home/santiago/.cargo/registry/src/github.com-1ecc6299db9ec823/sha2-0.5.3/src/lib.rs","byte_start":636,"byte_end":662,"line_start":14,"line_end":14,"column_start":1,"column_end":27}},{"value":"/","span":{"file_name":"/home/santiago/.cargo/registry/src/github.com-1ecc6299db9ec823/sha2-0.5.3/src/lib.rs","byte_start":663,"byte_end":666,"line_start":15,"line_end":15,"column_start":1,"column_end":4}},{"value":"/ Algorithmically, there are only 2 core algorithms: `Sha256` and `Sha512`.","span":{"file_name":"/home/santiago/.cargo/registry/src/github.com-1ecc6299db9ec823/sha2-0.5.3/src/lib.rs","byte_start":667,"byte_end":744,"line_start":16,"line_end":16,"column_start":1,"column_end":78}},{"value":"/ All other algorithms are just applications of these with different initial","span":{"file_name":"/home/santiago/.cargo/registry/src/github.com-1ecc6299db9ec823/sha2-0.5.3/src/lib.rs","byte_start":745,"byte_end":823,"line_start":17,"line_end":17,"column_start":1,"column_end":79}},{"value":"/ hash values, and truncated to different digest bit lengths.","span":{"file_name":"/home/santiago/.cargo/registry/src/github.com-1ecc6299db9ec823/sha2-0.5.3/src/lib.rs","byte_start":824,"byte_end":887,"line_start":18,"line_end":18,"column_start":1,"column_end":64}},{"value":"/","span":{"file_name":"/home/santiago/.cargo/registry/src/github.com-1ecc6299db9ec823/sha2-0.5.3/src/lib.rs","byte_start":888,"byte_end":891,"line_start":19,"line_end":19,"column_start":1,"column_end":4}},{"value":"/ # Usage","span":{"file_name":"/home/santiago/.cargo/registry/src/github.com-1ecc6299db9ec823/sha2-0.5.3/src/lib.rs","byte_start":892,"byte_end":903,"line_start":20,"line_end":20,"column_start":1,"column_end":12}},{"value":"/","span":{"file_name":"/home/santiago/.cargo/registry/src/github.com-1ecc6299db9ec823/sha2-0.5.3/src/lib.rs","byte_start":904,"byte_end":907,"line_start":21,"line_end":21,"column_start":1,"column_end":4}},{"value":"/ An example of using `Sha256` is:","span":{"file_name":"/home/santiago/.cargo/registry/src/github.com-1ecc6299db9ec823/sha2-0.5.3/src/lib.rs","byte_start":908,"byte_end":944,"line_start":22,"line_end":22,"column_start":1,"column_end":37}},{"value":"/","span":{"file_name":"/home/santiago/.cargo/registry/src/github.com-1ecc6299db9ec823/sha2-0.5.3/src/lib.rs","byte_start":945,"byte_end":948,"line_start":23,"line_end":23,"column_start":1,"column_end":4}},{"value":"/ ```rust","span":{"file_name":"/home/santiago/.cargo/registry/src/github.com-1ecc6299db9ec823/sha2-0.5.3/src/lib.rs","byte_start":949,"byte_end":960,"line_start":24,"line_end":24,"column_start":1,"column_end":12}},{"value":"/ use sha2::{Sha256, Digest};","span":{"file_name":"/home/santiago/.cargo/registry/src/github.com-1ecc6299db9ec823/sha2-0.5.3/src/lib.rs","byte_start":961,"byte_end":992,"line_start":25,"line_end":25,"column_start":1,"column_end":32}},{"value":"/","span":{"file_name":"/home/santiago/.cargo/registry/src/github.com-1ecc6299db9ec823/sha2-0.5.3/src/lib.rs","byte_start":993,"byte_end":996,"line_start":26,"line_end":26,"column_start":1,"column_end":4}},{"value":"/ // create a Sha256 object","span":{"file_name":"/home/santiago/.cargo/registry/src/github.com-1ecc6299db9ec823/sha2-0.5.3/src/lib.rs","byte_start":997,"byte_end":1026,"line_start":27,"line_end":27,"column_start":1,"column_end":30}},{"value":"/ let mut hasher = Sha256::default();","span":{"file_name":"/home/santiago/.cargo/registry/src/github.com-1ecc6299db9ec823/sha2-0.5.3/src/lib.rs","byte_start":1027,"byte_end":1066,"line_start":28,"line_end":28,"column_start":1,"column_end":40}},{"value":"/","span":{"file_name":"/home/santiago/.cargo/registry/src/github.com-1ecc6299db9ec823/sha2-0.5.3/src/lib.rs","byte_start":1067,"byte_end":1070,"line_start":29,"line_end":29,"column_start":1,"column_end":4}},{"value":"/ // write input message","span":{"file_name":"/home/santiago/.cargo/registry/src/github.com-1ecc6299db9ec823/sha2-0.5.3/src/lib.rs","byte_start":1071,"byte_end":1097,"line_start":30,"line_end":30,"column_start":1,"column_end":27}},{"value":"/ hasher.input(b\"hello world\");","span":{"file_name":"/home/santiago/.cargo/registry/src/github.com-1ecc6299db9ec823/sha2-0.5.3/src/lib.rs","byte_start":1098,"byte_end":1131,"line_start":31,"line_end":31,"column_start":1,"column_end":34}},{"value":"/","span":{"file_name":"/home/santiago/.cargo/registry/src/github.com-1ecc6299db9ec823/sha2-0.5.3/src/lib.rs","byte_start":1132,"byte_end":1135,"line_start":32,"line_end":32,"column_start":1,"column_end":4}},{"value":"/ // read hash digest and consume hasher","span":{"file_name":"/home/santiago/.cargo/registry/src/github.com-1ecc6299db9ec823/sha2-0.5.3/src/lib.rs","byte_start":1136,"byte_end":1178,"line_start":33,"line_end":33,"column_start":1,"column_end":43}},{"value":"/ let output = hasher.result();","span":{"file_name":"/home/santiago/.cargo/registry/src/github.com-1ecc6299db9ec823/sha2-0.5.3/src/lib.rs","byte_start":1179,"byte_end":1212,"line_start":34,"line_end":34,"column_start":1,"column_end":34}},{"value":"/","span":{"file_name":"/home/santiago/.cargo/registry/src/github.com-1ecc6299db9ec823/sha2-0.5.3/src/lib.rs","byte_start":1213,"byte_end":1216,"line_start":35,"line_end":35,"column_start":1,"column_end":4}},{"value":"/ assert_eq!(output[..], [0xb9, 0x4d, 0x27, 0xb9, 0x93, 0x4d, 0x3e, 0x08,","span":{"file_name":"/home/santiago/.cargo/registry/src/github.com-1ecc6299db9ec823/sha2-0.5.3/src/lib.rs","byte_start":1217,"byte_end":1292,"line_start":36,"line_end":36,"column_start":1,"column_end":76}},{"value":"/                         0xa5, 0x2e, 0x52, 0xd7, 0xda, 0x7d, 0xab, 0xfa,","span":{"file_name":"/home/santiago/.cargo/registry/src/github.com-1ecc6299db9ec823/sha2-0.5.3/src/lib.rs","byte_start":1293,"byte_end":1368,"line_start":37,"line_end":37,"column_start":1,"column_end":76}},{"value":"/                         0xc4, 0x84, 0xef, 0xe3, 0x7a, 0x53, 0x80, 0xee,","span":{"file_name":"/home/santiago/.cargo/registry/src/github.com-1ecc6299db9ec823/sha2-0.5.3/src/lib.rs","byte_start":1369,"byte_end":1444,"line_start":38,"line_end":38,"column_start":1,"column_end":76}},{"value":"/                         0x90, 0x88, 0xf7, 0xac, 0xe2, 0xef, 0xcd, 0xe9]);","span":{"file_name":"/home/santiago/.cargo/registry/src/github.com-1ecc6299db9ec823/sha2-0.5.3/src/lib.rs","byte_start":1445,"byte_end":1522,"line_start":39,"line_end":39,"column_start":1,"column_end":78}},{"value":"/ ```","span":{"file_name":"/home/santiago/.cargo/registry/src/github.com-1ecc6299db9ec823/sha2-0.5.3/src/lib.rs","byte_start":1523,"byte_end":1530,"line_start":40,"line_end":40,"column_start":1,"column_end":8}},{"value":"/","span":{"file_name":"/home/santiago/.cargo/registry/src/github.com-1ecc6299db9ec823/sha2-0.5.3/src/lib.rs","byte_start":1531,"byte_end":1534,"line_start":41,"line_end":41,"column_start":1,"column_end":4}},{"value":"/ An example of using `Sha512` is:","span":{"file_name":"/home/santiago/.cargo/registry/src/github.com-1ecc6299db9ec823/sha2-0.5.3/src/lib.rs","byte_start":1535,"byte_end":1571,"line_start":42,"line_end":42,"column_start":1,"column_end":37}},{"value":"/","span":{"file_name":"/home/santiago/.cargo/registry/src/github.com-1ecc6299db9ec823/sha2-0.5.3/src/lib.rs","byte_start":1572,"byte_end":1575,"line_start":43,"line_end":43,"column_start":1,"column_end":4}},{"value":"/ ```rust","span":{"file_name":"/home/santiago/.cargo/registry/src/github.com-1ecc6299db9ec823/sha2-0.5.3/src/lib.rs","byte_start":1576,"byte_end":1587,"line_start":44,"line_end":44,"column_start":1,"column_end":12}},{"value":"/ use sha2::{Sha512, Digest};","span":{"file_name":"/home/santiago/.cargo/registry/src/github.com-1ecc6299db9ec823/sha2-0.5.3/src/lib.rs","byte_start":1588,"byte_end":1619,"line_start":45,"line_end":45,"column_start":1,"column_end":32}},{"value":"/","span":{"file_name":"/home/santiago/.cargo/registry/src/github.com-1ecc6299db9ec823/sha2-0.5.3/src/lib.rs","byte_start":1620,"byte_end":1623,"line_start":46,"line_end":46,"column_start":1,"column_end":4}},{"value":"/ // create a Sha512 object","span":{"file_name":"/home/santiago/.cargo/registry/src/github.com-1ecc6299db9ec823/sha2-0.5.3/src/lib.rs","byte_start":1624,"byte_end":1653,"line_start":47,"line_end":47,"column_start":1,"column_end":30}},{"value":"/ let mut hasher = Sha512::default();","span":{"file_name":"/home/santiago/.cargo/registry/src/github.com-1ecc6299db9ec823/sha2-0.5.3/src/lib.rs","byte_start":1654,"byte_end":1693,"line_start":48,"line_end":48,"column_start":1,"column_end":40}},{"value":"/","span":{"file_name":"/home/santiago/.cargo/registry/src/github.com-1ecc6299db9ec823/sha2-0.5.3/src/lib.rs","byte_start":1694,"byte_end":1697,"line_start":49,"line_end":49,"column_start":1,"column_end":4}},{"value":"/ // write input message","span":{"file_name":"/home/santiago/.cargo/registry/src/github.com-1ecc6299db9ec823/sha2-0.5.3/src/lib.rs","byte_start":1698,"byte_end":1724,"line_start":50,"line_end":50,"column_start":1,"column_end":27}},{"value":"/ hasher.input(b\"hello world\");","span":{"file_name":"/home/santiago/.cargo/registry/src/github.com-1ecc6299db9ec823/sha2-0.5.3/src/lib.rs","byte_start":1725,"byte_end":1758,"line_start":51,"line_end":51,"column_start":1,"column_end":34}},{"value":"/","span":{"file_name":"/home/santiago/.cargo/registry/src/github.com-1ecc6299db9ec823/sha2-0.5.3/src/lib.rs","byte_start":1759,"byte_end":1762,"line_start":52,"line_end":52,"column_start":1,"column_end":4}},{"value":"/ // read hash digest and consume hasher","span":{"file_name":"/home/santiago/.cargo/registry/src/github.com-1ecc6299db9ec823/sha2-0.5.3/src/lib.rs","byte_start":1763,"byte_end":1805,"line_start":53,"line_end":53,"column_start":1,"column_end":43}},{"value":"/ let output = hasher.result();","span":{"file_name":"/home/santiago/.cargo/registry/src/github.com-1ecc6299db9ec823/sha2-0.5.3/src/lib.rs","byte_start":1806,"byte_end":1839,"line_start":54,"line_end":54,"column_start":1,"column_end":34}},{"value":"/","span":{"file_name":"/home/santiago/.cargo/registry/src/github.com-1ecc6299db9ec823/sha2-0.5.3/src/lib.rs","byte_start":1840,"byte_end":1843,"line_start":55,"line_end":55,"column_start":1,"column_end":4}},{"value":"/ assert_eq!(output[..], [0x30, 0x9e, 0xcc, 0x48, 0x9c, 0x12, 0xd6, 0xeb,","span":{"file_name":"/home/santiago/.cargo/registry/src/github.com-1ecc6299db9ec823/sha2-0.5.3/src/lib.rs","byte_start":1844,"byte_end":1919,"line_start":56,"line_end":56,"column_start":1,"column_end":76}},{"value":"/                         0x4c, 0xc4, 0x0f, 0x50, 0xc9, 0x02, 0xf2, 0xb4,","span":{"file_name":"/home/santiago/.cargo/registry/src/github.com-1ecc6299db9ec823/sha2-0.5.3/src/lib.rs","byte_start":1920,"byte_end":1995,"line_start":57,"line_end":57,"column_start":1,"column_end":76}},{"value":"/                         0xd0, 0xed, 0x77, 0xee, 0x51, 0x1a, 0x7c, 0x7a,","span":{"file_name":"/home/santiago/.cargo/registry/src/github.com-1ecc6299db9ec823/sha2-0.5.3/src/lib.rs","byte_start":1996,"byte_end":2071,"line_start":58,"line_end":58,"column_start":1,"column_end":76}},{"value":"/                         0x9b, 0xcd, 0x3c, 0xa8, 0x6d, 0x4c, 0xd8, 0x6f,","span":{"file_name":"/home/santiago/.cargo/registry/src/github.com-1ecc6299db9ec823/sha2-0.5.3/src/lib.rs","byte_start":2072,"byte_end":2147,"line_start":59,"line_end":59,"column_start":1,"column_end":76}},{"value":"/                         0x98, 0x9d, 0xd3, 0x5b, 0xc5, 0xff, 0x49, 0x96,","span":{"file_name":"/home/santiago/.cargo/registry/src/github.com-1ecc6299db9ec823/sha2-0.5.3/src/lib.rs","byte_start":2148,"byte_end":2223,"line_start":60,"line_end":60,"column_start":1,"column_end":76}},{"value":"/                         0x70, 0xda, 0x34, 0x25, 0x5b, 0x45, 0xb0, 0xcf,","span":{"file_name":"/home/santiago/.cargo/registry/src/github.com-1ecc6299db9ec823/sha2-0.5.3/src/lib.rs","byte_start":2224,"byte_end":2299,"line_start":61,"line_end":61,"column_start":1,"column_end":76}},{"value":"/                         0xd8, 0x30, 0xe8, 0x1f, 0x60, 0x5d, 0xcf, 0x7d,","span":{"file_name":"/home/santiago/.cargo/registry/src/github.com-1ecc6299db9ec823/sha2-0.5.3/src/lib.rs","byte_start":2300,"byte_end":2375,"line_start":62,"line_end":62,"column_start":1,"column_end":76}},{"value":"/                         0xc5, 0x54, 0x2e, 0x93, 0xae, 0x9c, 0xd7, 0x6f][..]);","span":{"file_name":"/home/santiago/.cargo/registry/src/github.com-1ecc6299db9ec823/sha2-0.5.3/src/lib.rs","byte_start":2376,"byte_end":2457,"line_start":63,"line_end":63,"column_start":1,"column_end":82}},{"value":"/ ```","span":{"file_name":"/home/santiago/.cargo/registry/src/github.com-1ecc6299db9ec823/sha2-0.5.3/src/lib.rs","byte_start":2458,"byte_end":2465,"line_start":64,"line_end":64,"column_start":1,"column_end":8}},{"value":"no_std","span":{"file_name":"/home/santiago/.cargo/registry/src/github.com-1ecc6299db9ec823/sha2-0.5.3/src/lib.rs","byte_start":2467,"byte_end":2477,"line_start":66,"line_end":66,"column_start":1,"column_end":11}}]},{"kind":"Struct","id":{"krate":0,"index":322},"span":{"file_name":"/home/santiago/.cargo/registry/src/github.com-1ecc6299db9ec823/sha2-0.5.3/src/sha256.rs","byte_start":34147,"byte_end":34153,"line_start":73,"line_end":73,"column_start":12,"column_end":18},"name":"Sha256","qualname":"::sha256::Sha256","value":"Sha256 {  }","parent":null,"children":[{"krate":0,"index":323}],"decl_id":null,"docs":" The SHA-256 hash algorithm with the SHA-256 initial hash value.\n","sig":null,"attributes":[{"value":"/ The SHA-256 hash algorithm with the SHA-256 initial hash value.","span":{"file_name":"/home/santiago/.cargo/registry/src/github.com-1ecc6299db9ec823/sha2-0.5.3/src/sha256.rs","byte_start":34045,"byte_end":34112,"line_start":71,"line_end":71,"column_start":1,"column_end":68}}]},{"kind":"Struct","id":{"krate":0,"index":327},"span":{"file_name":"/home/santiago/.cargo/registry/src/github.com-1ecc6299db9ec823/sha2-0.5.3/src/sha256.rs","byte_start":34846,"byte_end":34852,"line_start":101,"line_end":101,"column_start":12,"column_end":18},"name":"Sha224","qualname":"::sha256::Sha224","value":"Sha224 {  }","parent":null,"children":[{"krate":0,"index":328}],"decl_id":null,"docs":" The SHA-256 hash algorithm with the SHA-224 initial hash value. The result\n is truncated to 224 bits.\n","sig":null,"attributes":[{"value":"/ The SHA-256 hash algorithm with the SHA-224 initial hash value. The result","span":{"file_name":"/home/santiago/.cargo/registry/src/github.com-1ecc6299db9ec823/sha2-0.5.3/src/sha256.rs","byte_start":34703,"byte_end":34781,"line_start":98,"line_end":98,"column_start":1,"column_end":79}},{"value":"/ is truncated to 224 bits.","span":{"file_name":"/home/santiago/.cargo/registry/src/github.com-1ecc6299db9ec823/sha2-0.5.3/src/sha256.rs","byte_start":34782,"byte_end":34811,"line_start":99,"line_end":99,"column_start":1,"column_end":30}}]},{"kind":"Struct","id":{"krate":0,"index":346},"span":{"file_name":"/home/santiago/.cargo/registry/src/github.com-1ecc6299db9ec823/sha2-0.5.3/src/sha512.rs","byte_start":37720,"byte_end":37726,"line_start":78,"line_end":78,"column_start":12,"column_end":18},"name":"Sha512","qualname":"::sha512::Sha512","value":"Sha512 {  }","parent":null,"children":[{"krate":0,"index":347}],"decl_id":null,"docs":" The SHA-512 hash algorithm with the SHA-512 initial hash value.\n","sig":null,"attributes":[{"value":"/ The SHA-512 hash algorithm with the SHA-512 initial hash value.","span":{"file_name":"/home/santiago/.cargo/registry/src/github.com-1ecc6299db9ec823/sha2-0.5.3/src/sha512.rs","byte_start":37618,"byte_end":37685,"line_start":76,"line_end":76,"column_start":1,"column_end":68}}]},{"kind":"Struct","id":{"krate":0,"index":351},"span":{"file_name":"/home/santiago/.cargo/registry/src/github.com-1ecc6299db9ec823/sha2-0.5.3/src/sha512.rs","byte_start":38426,"byte_end":38432,"line_start":109,"line_end":109,"column_start":12,"column_end":18},"name":"Sha384","qualname":"::sha512::Sha384","value":"Sha384 {  }","parent":null,"children":[{"krate":0,"index":352}],"decl_id":null,"docs":" The SHA-512 hash algorithm with the SHA-384 initial hash value. The result\n is truncated to 384 bits.\n","sig":null,"attributes":[{"value":"/ The SHA-512 hash algorithm with the SHA-384 initial hash value. The result","span":{"file_name":"/home/santiago/.cargo/registry/src/github.com-1ecc6299db9ec823/sha2-0.5.3/src/sha512.rs","byte_start":38283,"byte_end":38361,"line_start":106,"line_end":106,"column_start":1,"column_end":79}},{"value":"/ is truncated to 384 bits.","span":{"file_name":"/home/santiago/.cargo/registry/src/github.com-1ecc6299db9ec823/sha2-0.5.3/src/sha512.rs","byte_start":38362,"byte_end":38391,"line_start":107,"line_end":107,"column_start":1,"column_end":30}}]},{"kind":"Struct","id":{"krate":0,"index":356},"span":{"file_name":"/home/santiago/.cargo/registry/src/github.com-1ecc6299db9ec823/sha2-0.5.3/src/sha512.rs","byte_start":39137,"byte_end":39151,"line_start":140,"line_end":140,"column_start":12,"column_end":26},"name":"Sha512Trunc256","qualname":"::sha512::Sha512Trunc256","value":"Sha512Trunc256 {  }","parent":null,"children":[{"krate":0,"index":357}],"decl_id":null,"docs":" The SHA-512 hash algorithm with the SHA-512/256 initial hash value. The\n result is truncated to 256 bits.\n","sig":null,"attributes":[{"value":"/ The SHA-512 hash algorithm with the SHA-512/256 initial hash value. The","span":{"file_name":"/home/santiago/.cargo/registry/src/github.com-1ecc6299db9ec823/sha2-0.5.3/src/sha512.rs","byte_start":38990,"byte_end":39065,"line_start":137,"line_end":137,"column_start":1,"column_end":76}},{"value":"/ result is truncated to 256 bits.","span":{"file_name":"/home/santiago/.cargo/registry/src/github.com-1ecc6299db9ec823/sha2-0.5.3/src/sha512.rs","byte_start":39066,"byte_end":39102,"line_start":138,"line_end":138,"column_start":1,"column_end":37}}]},{"kind":"Struct","id":{"krate":0,"index":361},"span":{"file_name":"/home/santiago/.cargo/registry/src/github.com-1ecc6299db9ec823/sha2-0.5.3/src/sha512.rs","byte_start":39908,"byte_end":39922,"line_start":171,"line_end":171,"column_start":12,"column_end":26},"name":"Sha512Trunc224","qualname":"::sha512::Sha512Trunc224","value":"Sha512Trunc224 {  }","parent":null,"children":[{"krate":0,"index":362}],"decl_id":null,"docs":" The SHA-512 hash algorithm with the SHA-512/224 initial hash value.\n The result is truncated to 224 bits.\n","sig":null,"attributes":[{"value":"/ The SHA-512 hash algorithm with the SHA-512/224 initial hash value.","span":{"file_name":"/home/santiago/.cargo/registry/src/github.com-1ecc6299db9ec823/sha2-0.5.3/src/sha512.rs","byte_start":39761,"byte_end":39832,"line_start":168,"line_end":168,"column_start":1,"column_end":72}},{"value":"/ The result is truncated to 224 bits.","span":{"file_name":"/home/santiago/.cargo/registry/src/github.com-1ecc6299db9ec823/sha2-0.5.3/src/sha512.rs","byte_start":39833,"byte_end":39873,"line_start":169,"line_end":169,"column_start":1,"column_end":41}}]}],"impls":[{"id":0,"kind":"Inherent","span":{"file_name":"/home/santiago/.cargo/registry/src/github.com-1ecc6299db9ec823/sha2-0.5.3/src/sha256.rs","byte_start":32586,"byte_end":32600,"line_start":24,"line_end":24,"column_start":6,"column_end":20},"value":"","parent":null,"children":[{"krate":0,"index":156},{"krate":0,"index":158}],"docs":"","sig":null,"attributes":[]},{"id":1,"kind":"Inherent","span":{"file_name":"/home/santiago/.cargo/registry/src/github.com-1ecc6299db9ec823/sha2-0.5.3/src/sha256.rs","byte_start":33064,"byte_end":33073,"line_start":41,"line_end":41,"column_start":6,"column_end":15},"value":"","parent":null,"children":[{"krate":0,"index":160},{"krate":0,"index":162},{"krate":0,"index":164}],"docs":"","sig":null,"attributes":[]},{"id":2,"kind":"Direct","span":{"file_name":"/home/santiago/.cargo/registry/src/github.com-1ecc6299db9ec823/sha2-0.5.3/src/sha256.rs","byte_start":34199,"byte_end":34205,"line_start":77,"line_end":77,"column_start":18,"column_end":24},"value":"","parent":null,"children":[{"krate":0,"index":167}],"docs":"","sig":null,"attributes":[]},{"id":3,"kind":"Direct","span":{"file_name":"/home/santiago/.cargo/registry/src/github.com-1ecc6299db9ec823/sha2-0.5.3/src/sha256.rs","byte_start":34304,"byte_end":34310,"line_start":81,"line_end":81,"column_start":24,"column_end":30},"value":"","parent":null,"children":[{"krate":0,"index":169},{"krate":0,"index":170}],"docs":"","sig":null,"attributes":[]},{"id":4,"kind":"Direct","span":{"file_name":"/home/santiago/.cargo/registry/src/github.com-1ecc6299db9ec823/sha2-0.5.3/src/sha256.rs","byte_start":34443,"byte_end":34449,"line_start":87,"line_end":87,"column_start":30,"column_end":36},"value":"","parent":null,"children":[{"krate":0,"index":172},{"krate":0,"index":173}],"docs":"","sig":null,"attributes":[]},{"id":5,"kind":"Direct","span":{"file_name":"/home/santiago/.cargo/registry/src/github.com-1ecc6299db9ec823/sha2-0.5.3/src/sha256.rs","byte_start":34898,"byte_end":34904,"line_start":105,"line_end":105,"column_start":18,"column_end":24},"value":"","parent":null,"children":[{"krate":0,"index":175}],"docs":"","sig":null,"attributes":[]},{"id":6,"kind":"Direct","span":{"file_name":"/home/santiago/.cargo/registry/src/github.com-1ecc6299db9ec823/sha2-0.5.3/src/sha256.rs","byte_start":35003,"byte_end":35009,"line_start":109,"line_end":109,"column_start":24,"column_end":30},"value":"","parent":null,"children":[{"krate":0,"index":177},{"krate":0,"index":178}],"docs":"","sig":null,"attributes":[]},{"id":7,"kind":"Direct","span":{"file_name":"/home/santiago/.cargo/registry/src/github.com-1ecc6299db9ec823/sha2-0.5.3/src/sha256.rs","byte_start":35142,"byte_end":35148,"line_start":115,"line_end":115,"column_start":30,"column_end":36},"value":"","parent":null,"children":[{"krate":0,"index":180},{"krate":0,"index":181}],"docs":"","sig":null,"attributes":[]},{"id":8,"kind":"Inherent","span":{"file_name":"/home/santiago/.cargo/registry/src/github.com-1ecc6299db9ec823/sha2-0.5.3/src/sha512.rs","byte_start":36090,"byte_end":36104,"line_start":25,"line_end":25,"column_start":6,"column_end":20},"value":"","parent":null,"children":[{"krate":0,"index":243},{"krate":0,"index":245}],"docs":"","sig":null,"attributes":[]},{"id":9,"kind":"Inherent","span":{"file_name":"/home/santiago/.cargo/registry/src/github.com-1ecc6299db9ec823/sha2-0.5.3/src/sha512.rs","byte_start":36567,"byte_end":36576,"line_start":42,"line_end":42,"column_start":6,"column_end":15},"value":"","parent":null,"children":[{"krate":0,"index":247},{"krate":0,"index":249},{"krate":0,"index":251}],"docs":"","sig":null,"attributes":[]},{"id":10,"kind":"Direct","span":{"file_name":"/home/santiago/.cargo/registry/src/github.com-1ecc6299db9ec823/sha2-0.5.3/src/sha512.rs","byte_start":37772,"byte_end":37778,"line_start":82,"line_end":82,"column_start":18,"column_end":24},"value":"","parent":null,"children":[{"krate":0,"index":254}],"docs":"","sig":null,"attributes":[]},{"id":11,"kind":"Direct","span":{"file_name":"/home/santiago/.cargo/registry/src/github.com-1ecc6299db9ec823/sha2-0.5.3/src/sha512.rs","byte_start":37877,"byte_end":37883,"line_start":86,"line_end":86,"column_start":24,"column_end":30},"value":"","parent":null,"children":[{"krate":0,"index":256},{"krate":0,"index":257}],"docs":"","sig":null,"attributes":[]},{"id":12,"kind":"Direct","span":{"file_name":"/home/santiago/.cargo/registry/src/github.com-1ecc6299db9ec823/sha2-0.5.3/src/sha512.rs","byte_start":38016,"byte_end":38022,"line_start":92,"line_end":92,"column_start":30,"column_end":36},"value":"","parent":null,"children":[{"krate":0,"index":259},{"krate":0,"index":260}],"docs":"","sig":null,"attributes":[]},{"id":13,"kind":"Direct","span":{"file_name":"/home/santiago/.cargo/registry/src/github.com-1ecc6299db9ec823/sha2-0.5.3/src/sha512.rs","byte_start":38478,"byte_end":38484,"line_start":113,"line_end":113,"column_start":18,"column_end":24},"value":"","parent":null,"children":[{"krate":0,"index":262}],"docs":"","sig":null,"attributes":[]},{"id":14,"kind":"Direct","span":{"file_name":"/home/santiago/.cargo/registry/src/github.com-1ecc6299db9ec823/sha2-0.5.3/src/sha512.rs","byte_start":38583,"byte_end":38589,"line_start":117,"line_end":117,"column_start":24,"column_end":30},"value":"","parent":null,"children":[{"krate":0,"index":264},{"krate":0,"index":265}],"docs":"","sig":null,"attributes":[]},{"id":15,"kind":"Direct","span":{"file_name":"/home/santiago/.cargo/registry/src/github.com-1ecc6299db9ec823/sha2-0.5.3/src/sha512.rs","byte_start":38722,"byte_end":38728,"line_start":123,"line_end":123,"column_start":30,"column_end":36},"value":"","parent":null,"children":[{"krate":0,"index":267},{"krate":0,"index":268}],"docs":"","sig":null,"attributes":[]},{"id":16,"kind":"Direct","span":{"file_name":"/home/santiago/.cargo/registry/src/github.com-1ecc6299db9ec823/sha2-0.5.3/src/sha512.rs","byte_start":39197,"byte_end":39211,"line_start":144,"line_end":144,"column_start":18,"column_end":32},"value":"","parent":null,"children":[{"krate":0,"index":270}],"docs":"","sig":null,"attributes":[]},{"id":17,"kind":"Direct","span":{"file_name":"/home/santiago/.cargo/registry/src/github.com-1ecc6299db9ec823/sha2-0.5.3/src/sha512.rs","byte_start":39340,"byte_end":39354,"line_start":150,"line_end":150,"column_start":24,"column_end":38},"value":"","parent":null,"children":[{"krate":0,"index":272},{"krate":0,"index":273}],"docs":"","sig":null,"attributes":[]},{"id":18,"kind":"Direct","span":{"file_name":"/home/santiago/.cargo/registry/src/github.com-1ecc6299db9ec823/sha2-0.5.3/src/sha512.rs","byte_start":39487,"byte_end":39501,"line_start":156,"line_end":156,"column_start":30,"column_end":44},"value":"","parent":null,"children":[{"krate":0,"index":275},{"krate":0,"index":276}],"docs":"","sig":null,"attributes":[]},{"id":19,"kind":"Direct","span":{"file_name":"/home/santiago/.cargo/registry/src/github.com-1ecc6299db9ec823/sha2-0.5.3/src/sha512.rs","byte_start":39968,"byte_end":39982,"line_start":175,"line_end":175,"column_start":18,"column_end":32},"value":"","parent":null,"children":[{"krate":0,"index":278}],"docs":"","sig":null,"attributes":[]},{"id":20,"kind":"Direct","span":{"file_name":"/home/santiago/.cargo/registry/src/github.com-1ecc6299db9ec823/sha2-0.5.3/src/sha512.rs","byte_start":40111,"byte_end":40125,"line_start":181,"line_end":181,"column_start":24,"column_end":38},"value":"","parent":null,"children":[{"krate":0,"index":280},{"krate":0,"index":281}],"docs":"","sig":null,"attributes":[]},{"id":21,"kind":"Direct","span":{"file_name":"/home/santiago/.cargo/registry/src/github.com-1ecc6299db9ec823/sha2-0.5.3/src/sha512.rs","byte_start":40258,"byte_end":40272,"line_start":187,"line_end":187,"column_start":30,"column_end":44},"value":"","parent":null,"children":[{"krate":0,"index":283},{"krate":0,"index":284}],"docs":"","sig":null,"attributes":[]}],"refs":[],"macro_refs":[],"relations":[{"span":{"file_name":"/home/santiago/.cargo/registry/src/github.com-1ecc6299db9ec823/sha2-0.5.3/src/sha256.rs","byte_start":32586,"byte_end":32600,"line_start":24,"line_end":24,"column_start":6,"column_end":20},"kind":{"Impl":{"id":0}},"from":{"krate":0,"index":308},"to":{"krate":4294967295,"index":4294967295}},{"span":{"file_name":"/home/santiago/.cargo/registry/src/github.com-1ecc6299db9ec823/sha2-0.5.3/src/sha256.rs","byte_start":33064,"byte_end":33073,"line_start":41,"line_end":41,"column_start":6,"column_end":15},"kind":{"Impl":{"id":1}},"from":{"krate":0,"index":315},"to":{"krate":4294967295,"index":4294967295}},{"span":{"file_name":"/home/santiago/.cargo/registry/src/github.com-1ecc6299db9ec823/sha2-0.5.3/src/sha256.rs","byte_start":34199,"byte_end":34205,"line_start":77,"line_end":77,"column_start":18,"column_end":24},"kind":{"Impl":{"id":2}},"from":{"krate":0,"index":322},"to":{"krate":1,"index":2800}},{"span":{"file_name":"/home/santiago/.cargo/registry/src/github.com-1ecc6299db9ec823/sha2-0.5.3/src/sha256.rs","byte_start":34304,"byte_end":34310,"line_start":81,"line_end":81,"column_start":24,"column_end":30},"kind":{"Impl":{"id":3}},"from":{"krate":0,"index":322},"to":{"krate":8,"index":12}},{"span":{"file_name":"/home/santiago/.cargo/registry/src/github.com-1ecc6299db9ec823/sha2-0.5.3/src/sha256.rs","byte_start":34443,"byte_end":34449,"line_start":87,"line_end":87,"column_start":30,"column_end":36},"kind":{"Impl":{"id":4}},"from":{"krate":0,"index":322},"to":{"krate":8,"index":15}},{"span":{"file_name":"/home/santiago/.cargo/registry/src/github.com-1ecc6299db9ec823/sha2-0.5.3/src/sha256.rs","byte_start":34898,"byte_end":34904,"line_start":105,"line_end":105,"column_start":18,"column_end":24},"kind":{"Impl":{"id":5}},"from":{"krate":0,"index":327},"to":{"krate":1,"index":2800}},{"span":{"file_name":"/home/santiago/.cargo/registry/src/github.com-1ecc6299db9ec823/sha2-0.5.3/src/sha256.rs","byte_start":35003,"byte_end":35009,"line_start":109,"line_end":109,"column_start":24,"column_end":30},"kind":{"Impl":{"id":6}},"from":{"krate":0,"index":327},"to":{"krate":8,"index":12}},{"span":{"file_name":"/home/santiago/.cargo/registry/src/github.com-1ecc6299db9ec823/sha2-0.5.3/src/sha256.rs","byte_start":35142,"byte_end":35148,"line_start":115,"line_end":115,"column_start":30,"column_end":36},"kind":{"Impl":{"id":7}},"from":{"krate":0,"index":327},"to":{"krate":8,"index":15}},{"span":{"file_name":"/home/santiago/.cargo/registry/src/github.com-1ecc6299db9ec823/sha2-0.5.3/src/sha512.rs","byte_start":36090,"byte_end":36104,"line_start":25,"line_end":25,"column_start":6,"column_end":20},"kind":{"Impl":{"id":8}},"from":{"krate":0,"index":332},"to":{"krate":4294967295,"index":4294967295}},{"span":{"file_name":"/home/santiago/.cargo/registry/src/github.com-1ecc6299db9ec823/sha2-0.5.3/src/sha512.rs","byte_start":36567,"byte_end":36576,"line_start":42,"line_end":42,"column_start":6,"column_end":15},"kind":{"Impl":{"id":9}},"from":{"krate":0,"index":339},"to":{"krate":4294967295,"index":4294967295}},{"span":{"file_name":"/home/santiago/.cargo/registry/src/github.com-1ecc6299db9ec823/sha2-0.5.3/src/sha512.rs","byte_start":37772,"byte_end":37778,"line_start":82,"line_end":82,"column_start":18,"column_end":24},"kind":{"Impl":{"id":10}},"from":{"krate":0,"index":346},"to":{"krate":1,"index":2800}},{"span":{"file_name":"/home/santiago/.cargo/registry/src/github.com-1ecc6299db9ec823/sha2-0.5.3/src/sha512.rs","byte_start":37877,"byte_end":37883,"line_start":86,"line_end":86,"column_start":24,"column_end":30},"kind":{"Impl":{"id":11}},"from":{"krate":0,"index":346},"to":{"krate":8,"index":12}},{"span":{"file_name":"/home/santiago/.cargo/registry/src/github.com-1ecc6299db9ec823/sha2-0.5.3/src/sha512.rs","byte_start":38016,"byte_end":38022,"line_start":92,"line_end":92,"column_start":30,"column_end":36},"kind":{"Impl":{"id":12}},"from":{"krate":0,"index":346},"to":{"krate":8,"index":15}},{"span":{"file_name":"/home/santiago/.cargo/registry/src/github.com-1ecc6299db9ec823/sha2-0.5.3/src/sha512.rs","byte_start":38478,"byte_end":38484,"line_start":113,"line_end":113,"column_start":18,"column_end":24},"kind":{"Impl":{"id":13}},"from":{"krate":0,"index":351},"to":{"krate":1,"index":2800}},{"span":{"file_name":"/home/santiago/.cargo/registry/src/github.com-1ecc6299db9ec823/sha2-0.5.3/src/sha512.rs","byte_start":38583,"byte_end":38589,"line_start":117,"line_end":117,"column_start":24,"column_end":30},"kind":{"Impl":{"id":14}},"from":{"krate":0,"index":351},"to":{"krate":8,"index":12}},{"span":{"file_name":"/home/santiago/.cargo/registry/src/github.com-1ecc6299db9ec823/sha2-0.5.3/src/sha512.rs","byte_start":38722,"byte_end":38728,"line_start":123,"line_end":123,"column_start":30,"column_end":36},"kind":{"Impl":{"id":15}},"from":{"krate":0,"index":351},"to":{"krate":8,"index":15}},{"span":{"file_name":"/home/santiago/.cargo/registry/src/github.com-1ecc6299db9ec823/sha2-0.5.3/src/sha512.rs","byte_start":39197,"byte_end":39211,"line_start":144,"line_end":144,"column_start":18,"column_end":32},"kind":{"Impl":{"id":16}},"from":{"krate":0,"index":356},"to":{"krate":1,"index":2800}},{"span":{"file_name":"/home/santiago/.cargo/registry/src/github.com-1ecc6299db9ec823/sha2-0.5.3/src/sha512.rs","byte_start":39340,"byte_end":39354,"line_start":150,"line_end":150,"column_start":24,"column_end":38},"kind":{"Impl":{"id":17}},"from":{"krate":0,"index":356},"to":{"krate":8,"index":12}},{"span":{"file_name":"/home/santiago/.cargo/registry/src/github.com-1ecc6299db9ec823/sha2-0.5.3/src/sha512.rs","byte_start":39487,"byte_end":39501,"line_start":156,"line_end":156,"column_start":30,"column_end":44},"kind":{"Impl":{"id":18}},"from":{"krate":0,"index":356},"to":{"krate":8,"index":15}},{"span":{"file_name":"/home/santiago/.cargo/registry/src/github.com-1ecc6299db9ec823/sha2-0.5.3/src/sha512.rs","byte_start":39968,"byte_end":39982,"line_start":175,"line_end":175,"column_start":18,"column_end":32},"kind":{"Impl":{"id":19}},"from":{"krate":0,"index":361},"to":{"krate":1,"index":2800}},{"span":{"file_name":"/home/santiago/.cargo/registry/src/github.com-1ecc6299db9ec823/sha2-0.5.3/src/sha512.rs","byte_start":40111,"byte_end":40125,"line_start":181,"line_end":181,"column_start":24,"column_end":38},"kind":{"Impl":{"id":20}},"from":{"krate":0,"index":361},"to":{"krate":8,"index":12}},{"span":{"file_name":"/home/santiago/.cargo/registry/src/github.com-1ecc6299db9ec823/sha2-0.5.3/src/sha512.rs","byte_start":40258,"byte_end":40272,"line_start":187,"line_end":187,"column_start":30,"column_end":44},"kind":{"Impl":{"id":21}},"from":{"krate":0,"index":361},"to":{"krate":8,"index":15}}]}